grappa/__init__.py
grappa/constants.py
grappa/grappa.py
grappa/units.py
grappa/data/__init__.py
grappa/data/comparison_parameters.png
grappa/data/dataset.py
grappa/data/dataset_builder.py
grappa/data/graph_data_loader.py
grappa/data/grappa_data.py
grappa/data/mol_data.py
grappa/data/molecule.py
grappa/data/parameters.py
grappa/data/published_datasets.csv
grappa/data/random_parameters.png
grappa/models/__init__.py
grappa/models/energy.py
grappa/models/final_layer.py
grappa/models/graph_attention.py
grappa/models/grappa.py
grappa/models/interaction_parameters.py
grappa/models/internal_coordinates.py
grappa/models/network_utils.py
grappa/models/perm_equiv_transformer.py
grappa/models/published_models.csv
grappa/training/__init__.py
grappa/training/evaluator.py
grappa/training/experiment.py
grappa/training/export_model.py
grappa/training/lightning_model.py
grappa/training/loss.py
grappa/utils/__init__.py
grappa/utils/data_utils.py
grappa/utils/dgl_utils.py
grappa/utils/graph_utils.py
grappa/utils/gromacs_utils.py
grappa/utils/hyp_dop_utility.py
grappa/utils/kimmdy_utils.py
grappa/utils/model_loading_utils.py
grappa/utils/openff_utils.py
grappa/utils/openmm_utils.py
grappa/utils/plotting.py
grappa/utils/rdkit_utils.py
grappa/utils/run_utils.py
grappa/utils/system_utils.py
grappa/utils/torch_utils.py
grappa/utils/training_utils.py
grappa/utils/tuple_indices.py
grappa/utils/visualization.py
grappa/utils/classical_forcefields/amber99sbildn-star_.xml
grappa/utils/classical_forcefields/charmm36-jul2022.xml
grappa/utils/classical_forcefields/tip3p_standard.xml
grappa/utils/compare_plots_amber/uncapped-300K-amber99/contribution_comparison.png
grappa/utils/compare_plots_amber/uncapped-300K-amber99/energy_comparison.png
grappa/utils/compare_plots_amber/uncapped-300K-amber99/force_comparison.png
grappa/utils/plots/uncapped-300K-amber99/contributions.png
grappa/utils/plots/uncapped-300K-amber99/energy.png
grappa/utils/plots/uncapped-300K-amber99/energy_rmsd_histogram.png
grappa_ff-1.4.0.dist-info/LICENSE
grappa_ff-1.4.0.dist-info/METADATA
grappa_ff-1.4.0.dist-info/WHEEL
grappa_ff-1.4.0.dist-info/entry_points.txt
grappa_ff-1.4.0.dist-info/top_level.txt
grappa_ff-1.4.0.dist-info/RECORD
