Metadata-Version: 2.2
Name: grappa-ff
Version: 1.4.0
Summary: Machine Learned Molecular Mechanics Force Field
Author-email: Leif Seute <leif.seute@h-its.org>
License:                     GNU GENERAL PUBLIC LICENSE
Requires-Python: >=3.10
License-File: LICENSE
Requires-Dist: numpy<=1.26.4
Requires-Dist: scipy>=1.13.0
Requires-Dist: pyyaml>=6.0.1
Requires-Dist: tqdm>=4.66.4
Requires-Dist: pandas>=2.2.0
Requires-Dist: pydantic>=2.7.1
Requires-Dist: seaborn>=0.13.2
Requires-Dist: rdkit>=2023.9.1
Requires-Dist: matplotlib>=3.8.2
Requires-Dist: wandb>=0.16.1
Requires-Dist: networkx>=3.2.1
Requires-Dist: charset-normalizer>=2.1.0
Requires-Dist: hydra-core>=1.3.2
Requires-Dist: pytest>=8.3.4
Requires-Dist: lightning==2.3.3
Requires-Dist: torchdata==0.7.1
Requires-Dist: torch==2.0.0
Requires-Dist: dgl==2.1.0
